{
  "title": "Parley MiC White Aho",
  "photos": [
    {
      "id": "72177720329243892-01",
      "title": "",
      "thumb": "https://img.libertybelljerseys.com/albums/parley-mic-white-aho/thumb/01.jpg",
      "full": "https://img.libertybelljerseys.com/albums/parley-mic-white-aho/full/01.jpg"
    },
    {
      "id": "72177720329243892-02",
      "title": "",
      "thumb": "https://img.libertybelljerseys.com/albums/parley-mic-white-aho/thumb/02.jpg",
      "full": "https://img.libertybelljerseys.com/albums/parley-mic-white-aho/full/02.jpg"
    },
    {
      "id": "72177720329243892-03",
      "title": "",
      "thumb": "https://img.libertybelljerseys.com/albums/parley-mic-white-aho/thumb/03.jpg",
      "full": "https://img.libertybelljerseys.com/albums/parley-mic-white-aho/full/03.jpg"
    },
    {
      "id": "72177720329243892-04",
      "title": "",
      "thumb": "https://img.libertybelljerseys.com/albums/parley-mic-white-aho/thumb/04.jpg",
      "full": "https://img.libertybelljerseys.com/albums/parley-mic-white-aho/full/04.jpg"
    }
  ]
}